hamqa/__init__.py
hamqa/hamqa.py
hamqa/hamqa_mpy.py
hamqa-0.5.0.dist-info/LICENSE
hamqa-0.5.0.dist-info/METADATA
hamqa-0.5.0.dist-info/WHEEL
hamqa-0.5.0.dist-info/RECORD
