Metadata-Version: 2.1
Name: hamqa
Version: 0.5.0
Summary: Home Assistant MQTT autodiscovery sensor registration and publishing library
Home-page: https://github.com/hvalev/hamqa
License: MIT
Author: hvalev
Requires-Python: >=3.8
Classifier: License :: OSI Approved :: MIT License
Classifier: Operating System :: OS Independent
Classifier: Programming Language :: Python :: 3
Classifier: Programming Language :: Python :: 3.8
Classifier: Programming Language :: Python :: 3.9
Classifier: Programming Language :: Python :: 3.10
Classifier: Programming Language :: Python :: 3.11
Classifier: Programming Language :: Python :: 3.12
Classifier: Programming Language :: Python :: 3.13
Requires-Dist: paho-mqtt (>=2.1.0,<3.0.0)
